MANIFEST.in
README.rst
setup.py
bin/ReadFromSharedMem
bin/WriteToSharedMem
mem_files/mem_map_file
wicomm/SharedMemIf.py
wicomm/SharedMemoryReader.py
wicomm/SharedMemoryWriter.py
wicomm/UdpDataSource.py
wicomm/WirelessDataSource.py
wicomm/__init__.py
wicomm.egg-info/PKG-INFO
wicomm.egg-info/SOURCES.txt
wicomm.egg-info/dependency_links.txt
wicomm.egg-info/not-zip-safe
wicomm.egg-info/top_level.txt