Metadata-Version: 1.1
Name: wicomm
Version: 0.12
Summary: Python package containing a wireless communication API to be used in robotics applications.
Home-page: http://hardworkin-man.com:8080/scm/git/wicomm
Author: Mike Moore
Author-email: mickety.mike@gmail.com
License: MIT
Keywords: wicomm
Platform: UNKNOWN
Classifier: Development Status :: 3 - Alpha
Classifier: License :: OSI Approved :: MIT License
Classifier: Programming Language :: Python :: 2.7
Classifier: Topic :: Text Processing :: Linguistic
